hikecalc/__init__.py
hikecalc/cli.py
hikecalc/gc_waypoints.py
hikecalc/geoloc.py
hikecalc/graph.yaml
hikecalc/graph_schema.sql
hikecalc/hike_calc.py
hikecalc/tt
hikecalc-0.6.0a1.dev3.dist-info/LICENSE
hikecalc-0.6.0a1.dev3.dist-info/WHEEL
hikecalc-0.6.0a1.dev3.dist-info/METADATA
hikecalc-0.6.0a1.dev3.dist-info/RECORD
